pgf.cp36-win_amd64.pyd
pgf_majestic-2.9.data/data/pgf.pyi
pgf_majestic-2.9.dist-info/METADATA
pgf_majestic-2.9.dist-info/WHEEL
pgf_majestic-2.9.dist-info/top_level.txt
pgf_majestic-2.9.dist-info/RECORD
