Metadata-Version: 2.1
Name: pgf-majestic
Version: 2.9
Summary: Python bindings to the Grammatical Framework's PGF runtime
Home-page: https://www.grammaticalframework.org/
Author: Krasimir Angelov
Author-email: kr.angelov@gmail.com
License: BSD
